[
  {
    "obj_id": "536",
    "obj_type": "Car",
    "psr": {
      "position": {
        "x": 5.879819804472371,
        "y": 5.6848722119813955,
        "z": -0.9796774983406067
      },
      "rotation": {
        "x": 0,
        "y": 0,
        "z": 0.02617993877991494
      },
      "scale": {
        "x": 3.8904640335106917,
        "y": 1.5909997370886302,
        "z": 1.3314629793167114
      }
    }
  },
  {
    "obj_id": "537",
    "obj_type": "Car",
    "psr": {
      "position": {
        "x": -10.465485234611542,
        "y": 4.092718102491345,
        "z": -1.5338654816150665
      },
      "rotation": {
        "x": 0,
        "y": 0,
        "z": 0.1832595714594046
      },
      "scale": {
        "x": 3.715484160712629,
        "y": 1.8052520253924134,
        "z": 1.5180749297142029
      }
    }
  },
  {
    "obj_id": "538",
    "obj_type": "Car",
    "psr": {
      "position": {
        "x": -9.382569325738034,
        "y": -6.412344366275934,
        "z": -1.3505255430936813
      },
      "rotation": {
        "x": 0,
        "y": 0,
        "z": 0.1308996938995747
      },
      "scale": {
        "x": 3.9605211084980882,
        "y": 1.702898688752224,
        "z": 1.7886010706424713
      }
    }
  },
  {
    "obj_id": "539",
    "obj_type": "Car",
    "psr": {
      "position": {
        "x": -7.509095133159464,
        "y": -1.5893653210802428,
        "z": -1.0034483792450581
      },
      "rotation": {
        "x": 0,
        "y": 0,
        "z": 0.07853981633974483
      },
      "scale": {
        "x": 2.423091886447553,
        "y": 1.8821883175794734,
        "z": 0.6020667795472454
      }
    }
  },
  {
    "obj_id": "540",
    "obj_type": "Car",
    "psr": {
      "position": {
        "x": 6.431771014579974,
        "y": 0.8190050814192373,
        "z": -0.4803390186280012
      },
      "rotation": {
        "x": 0,
        "y": 0,
        "z": 0.07853981633974483
      },
      "scale": {
        "x": 2.1760722857063977,
        "y": 1.588055406080762,
        "z": 1.060056034475565
      }
    }
  },
  {
    "obj_id": "541",
    "obj_type": "Car",
    "psr": {
      "position": {
        "x": 6.795461874740586,
        "y": 3.068025898546614,
        "z": -0.8418959826231003
      },
      "rotation": {
        "x": 0,
        "y": 0,
        "z": 0.02617993877991494
      },
      "scale": {
        "x": 1.8949155417983827,
        "y": 1.5683103368200273,
        "z": 0.9115079939365387
      }
    }
  },
  {
    "obj_id": "542",
    "obj_type": "Trimotorcycle",
    "psr": {
      "position": {
        "x": -6.596168713319186,
        "y": 0.2916667486275642,
        "z": -0.8950915038585663
      },
      "rotation": {
        "x": 0,
        "y": 0,
        "z": 0.02617993877991494
      },
      "scale": {
        "x": 2.113106948426175,
        "y": 1.3260614725536044,
        "z": 0.7815709710121155
      }
    }
  },
  {
    "obj_id": "543",
    "obj_type": "Car",
    "psr": {
      "position": {
        "x": 8.530198721036118,
        "y": -6.251479894828053,
        "z": -0.7099950164556503
      },
      "rotation": {
        "x": 0,
        "y": 0,
        "z": 0.1308996938995747
      },
      "scale": {
        "x": 3.2177688818514225,
        "y": 1.3668648831306185,
        "z": 0.9801960289478302
      }
    }
  },
  {
    "obj_id": "544",
    "obj_type": "Car",
    "psr": {
      "position": {
        "x": 2.538789525193664,
        "y": -6.966203329894823,
        "z": -0.6246963322169816
      },
      "rotation": {
        "x": 0,
        "y": 0,
        "z": 0.1308996938995747
      },
      "scale": {
        "x": 3.598223725250069,
        "y": 1.5439184027099957,
        "z": 0.717186665536411
      }
    }
  },
  {
    "obj_id": "545",
    "obj_type": "Car",
    "psr": {
      "position": {
        "x": -4.546837124510243,
        "y": -7.801135983631399,
        "z": -1.0268974538645648
      },
      "rotation": {
        "x": 0,
        "y": 0,
        "z": 0.23561944901923448
      },
      "scale": {
        "x": 4.038524887136127,
        "y": 1.4580507958971287,
        "z": 1.1657149068517494
      }
    }
  },
  {
    "obj_id": "546",
    "obj_type": "Car",
    "psr": {
      "position": {
        "x": 10.357129377551175,
        "y": -1.2866316696874711,
        "z": -1.0599824786186218
      },
      "rotation": {
        "x": 0,
        "y": 0,
        "z": 0.1832595714594046
      },
      "scale": {
        "x": 3.8941534707640293,
        "y": 1.7257471344674904,
        "z": 1.501608967781067
      }
    }
  },
  {
    "obj_id": "547",
    "obj_type": "Car",
    "psr": {
      "position": {
        "x": -12.740211822311052,
        "y": -4.460651605031404,
        "z": -1.570928543806076
      },
      "rotation": {
        "x": 0,
        "y": 0,
        "z": 0.23561944901923448
      },
      "scale": {
        "x": 2.980119409672801,
        "y": 1.3503525876773321,
        "z": 1.3957090973854065
      }
    }
  },
  {
    "obj_id": "548",
    "obj_type": "Car",
    "psr": {
      "position": {
        "x": 13.435597559234763,
        "y": 3.354905707860918,
        "z": -0.6604759991168976
      },
      "rotation": {
        "x": 0,
        "y": 0,
        "z": 0.1465407510765578
      },
      "scale": {
        "x": 1.3818959657510332,
        "y": 1.4015751276617345,
        "z": 1.0034520030021667
      }
    }
  },
  {
    "obj_id": "549",
    "obj_type": "Car",
    "psr": {
      "position": {
        "x": 10.935665236395018,
        "y": 5.654221028779834,
        "z": -0.8104910012334585
      },
      "rotation": {
        "x": 0,
        "y": 0,
        "z": 0.02617993877991494
      },
      "scale": {
        "x": 3.2897104099687846,
        "y": 1.5629312578936065,
        "z": 1.5183460004627705
      }
    }
  },
  {
    "obj_id": "550",
    "obj_type": "Motorcycle",
    "psr": {
      "position": {
        "x": 4.971272765046608,
        "y": 8.234666915875346,
        "z": -0.9863670021295547
      },
      "rotation": {
        "x": 0,
        "y": 0,
        "z": -0.14495956181848837
      },
      "scale": {
        "x": 1.0932964189910268,
        "y": 0.6900162652601565,
        "z": 1.3277439773082733
      }
    }
  },
  {
    "obj_id": "551",
    "obj_type": "Motorcycle",
    "psr": {
      "position": {
        "x": -1.3230042843805947,
        "y": 8.29379176541206,
        "z": -1.018784999847412
      },
      "rotation": {
        "x": 0,
        "y": 0,
        "z": 0.16963285556251875
      },
      "scale": {
        "x": 1.664043783308421,
        "y": 0.8268982968247941,
        "z": 1.0009779930114746
      }
    }
  },
  {
    "obj_id": "552",
    "obj_type": "Car",
    "psr": {
      "position": {
        "x": 13.625885621838478,
        "y": 10.843300581986284,
        "z": -0.743286982178688
      },
      "rotation": {
        "x": 0,
        "y": 0,
        "z": -0.6993917901896094
      },
      "scale": {
        "x": 3.2431801506516624,
        "y": 1.8606015409052308,
        "z": 1.152595967054367
      }
    }
  },
  {
    "obj_id": "553",
    "obj_type": "Motorcycle",
    "psr": {
      "position": {
        "x": 1.4361829136540465,
        "y": 5.5044364803608365,
        "z": -0.7032704949378967
      },
      "rotation": {
        "x": 0,
        "y": 0,
        "z": 0.16439388543773426
      },
      "scale": {
        "x": 1.5410559537542754,
        "y": 0.7663078165294945,
        "z": 0.5821889638900757
      }
    }
  },
  {
    "obj_id": "554",
    "obj_type": "Car",
    "psr": {
      "position": {
        "x": 1.0323087101982815,
        "y": -5.053407969242371,
        "z": -0.8178514568155872
      },
      "rotation": {
        "x": 0,
        "y": 0,
        "z": 0.21501521764734874
      },
      "scale": {
        "x": 2.7262565892156996,
        "y": 1.6884235264809109,
        "z": 0.704364901412699
      }
    }
  },
  {
    "obj_id": "555",
    "obj_type": "Motorcycle",
    "psr": {
      "position": {
        "x": -7.836943769790142,
        "y": -3.5186372024405617,
        "z": -1.0723085115079118
      },
      "rotation": {
        "x": 0,
        "y": 0,
        "z": 0.11014701336169952
      },
      "scale": {
        "x": 1.531252712898626,
        "y": 0.8917769296934983,
        "z": 1.1531617414787418
      }
    }
  },
  {
    "obj_id": "556",
    "obj_type": "Motorcycle",
    "psr": {
      "position": {
        "x": 7.498163306069375,
        "y": -2.7924231033279674,
        "z": -0.8843074157369853
      },
      "rotation": {
        "x": 0,
        "y": 0,
        "z": 0.17900354531886783
      },
      "scale": {
        "x": 1.6990613663445238,
        "y": 0.6961514482393149,
        "z": 1.368036252248492
      }
    }
  },
  {
    "obj_id": "557",
    "obj_type": "Motorcycle",
    "psr": {
      "position": {
        "x": 2.029169253345988,
        "y": 6.707651108988527,
        "z": -0.8095864653587341
      },
      "rotation": {
        "x": 0,
        "y": 0,
        "z": 0.14294364428901332
      },
      "scale": {
        "x": 1.1298374732817482,
        "y": 0.6555519420512826,
        "z": 0.8348549604415894
      }
    }
  },
  {
    "obj_id": "558",
    "obj_type": "Scooter",
    "psr": {
      "position": {
        "x": 2.2343770386111794,
        "y": 4.625196601881852,
        "z": -0.6485557475994791
      },
      "rotation": {
        "x": 0,
        "y": 0,
        "z": 0.10714940174378638
      },
      "scale": {
        "x": 1.1202417780075964,
        "y": 0.7449651532427223,
        "z": 0.7735605694063047
      }
    }
  },
  {
    "obj_id": "559",
    "obj_type": "Motorcycle",
    "psr": {
      "position": {
        "x": -4.4592695117477925,
        "y": 4.405597695546256,
        "z": -0.8302149772644043
      },
      "rotation": {
        "x": 0,
        "y": 0,
        "z": 0.6952212369956591
      },
      "scale": {
        "x": 1.3106350805284974,
        "y": 0.7718623957872283,
        "z": 0.5715999603271484
      }
    }
  },
  {
    "obj_id": "560",
    "obj_type": "Motorcycle",
    "psr": {
      "position": {
        "x": -1.4752031314416179,
        "y": 6.115227863207682,
        "z": -0.8591856669134675
      },
      "rotation": {
        "x": 0,
        "y": 0,
        "z": 0.1603633550975499
      },
      "scale": {
        "x": 0.8733512879290625,
        "y": 0.7398245858276121,
        "z": 0.6955133101834414
      }
    }
  },
  {
    "obj_id": "561",
    "obj_type": "Car",
    "psr": {
      "position": {
        "x": 9.712449941106053,
        "y": -3.924915933339634,
        "z": -0.9797464907169342
      },
      "rotation": {
        "x": 0,
        "y": 0,
        "z": 0.1832595714594046
      },
      "scale": {
        "x": 3.431307179581597,
        "y": 1.4364239952050282,
        "z": 1.5104829668998718
      }
    }
  },
  {
    "obj_id": "562",
    "obj_type": "Motorcycle",
    "psr": {
      "position": {
        "x": -2.7009990944843643,
        "y": -5.1272190319492115,
        "z": -0.7182050049304962
      },
      "rotation": {
        "x": 0,
        "y": 0,
        "z": 0.316835755469972
      },
      "scale": {
        "x": 0.7147581017866517,
        "y": 0.6802908375765211,
        "z": 0.6218339800834656
      }
    }
  }
]